lecture_automator/__init__.py
lecture_automator/cli.py
lecture_automator/compiler.py
lecture_automator/gen_speech/__init__.py
lecture_automator/gen_speech/exceptions.py
lecture_automator/gen_speech/gen_speech.py
lecture_automator/gen_speech/utils.py
lecture_automator/gen_video/__init__.py
lecture_automator/gen_video/gen_video.py
lecture_automator/marp_api/__init__.py
lecture_automator/marp_api/exceptions.py
lecture_automator/marp_api/marp_api.py
lecture_automator/parser/__init__.py
lecture_automator/parser/command_handler.py
lecture_automator/parser/exceptions.py
lecture_automator/parser/parser.py
lecture_automator/settings.py
lecture_automator/web.py
lecture_automator-1.1.2.dist-info/METADATA
lecture_automator-1.1.2.dist-info/WHEEL
lecture_automator-1.1.2.dist-info/entry_points.txt
lecture_automator-1.1.2.dist-info/RECORD
