Metadata-Version: 2.1
Name: lecture-automator
Version: 1.1.2
Summary: 
Home-page: https://github.com/CapBlood/lecture-automator.git
Author: CapBlood
Author-email: stalker.anonim@mail.ru
Requires-Python: >=3.8,<=3.9
Classifier: Programming Language :: Python :: 3
Classifier: Programming Language :: Python :: 3.8
Classifier: Programming Language :: Python :: 3.9
Provides-Extra: test
Requires-Dist: click (>=8.1.3,<9.0.0)
Requires-Dist: moviepy (>=1.0.3,<2.0.0)
Requires-Dist: numpy (>=1.24.2,<2.0.0)
Requires-Dist: streamlit (>=1.22.0,<2.0.0)
Requires-Dist: sympy (>=1.11.1,<2.0.0)
Requires-Dist: torch (>=2.0.0,<3.0.0)
Requires-Dist: tqdm (>=4.65.0,<5.0.0)
